vsphere_mcp_server/__init__.py
vsphere_mcp_server/credentials.py
vsphere_mcp_server/server.py
vsphere_mcp_server/vsphere_client.py
vsphere_mcp_server-0.1.0.dist-info/LICENSE
vsphere_mcp_server-0.1.0.dist-info/METADATA
vsphere_mcp_server-0.1.0.dist-info/WHEEL
vsphere_mcp_server-0.1.0.dist-info/entry_points.txt
vsphere_mcp_server-0.1.0.dist-info/top_level.txt
vsphere_mcp_server-0.1.0.dist-info/RECORD
